[{"code":"1102052005","district_code":"110205","name":"SALANG ALAS","postal_code":"24666"},{"code":"1102052009","district_code":"110205","name":"KUTA PASIR","postal_code":"24666"},{"code":"1102052011","district_code":"110205","name":"PURWODADI","postal_code":"24666"},{"code":"1102052012","district_code":"110205","name":"KUTA TINGGI","postal_code":"24666"},{"code":"1102052013","district_code":"110205","name":"KAMPUNG BARU","postal_code":"24666"},{"code":"1102052014","district_code":"110205","name":"PERANGINAN","postal_code":"24666"},{"code":"1102052015","district_code":"110205","name":"NATAM","postal_code":"24666"},{"code":"1102052025","district_code":"110205","name":"KUMBANG JAYA","postal_code":"24666"},{"code":"1102052026","district_code":"110205","name":"KUMBANG INDAH","postal_code":"24666"},{"code":"1102052027","district_code":"110205","name":"NATAM BARU","postal_code":"24666"},{"code":"1102052029","district_code":"110205","name":"DELENG MEGAKHE","postal_code":"24666"},{"code":"1102052030","district_code":"110205","name":"LAWE BEKUNG","postal_code":"24666"},{"code":"1102052031","district_code":"110205","name":"LAWE BEKUNG TAMPAHAN","postal_code":"24666"},{"code":"1102052032","district_code":"110205","name":"BADAR INDAH","postal_code":"24666"},{"code":"1102052033","district_code":"110205","name":"BATU MBEKHONG","postal_code":"24666"},{"code":"1102052034","district_code":"110205","name":"TANAH MERAH","postal_code":"24666"},{"code":"1102052035","district_code":"110205","name":"TANOH MEGAKHE","postal_code":"24666"},{"code":"1102052036","district_code":"110205","name":"LAWE SEKERAH","postal_code":"24666"}]