[{"code":"1208192001","district_code":"120819","name":"JAWA MARAJA","postal_code":"21153"},{"code":"1208192002","district_code":"120819","name":"MOHO","postal_code":"21153"},{"code":"1208192003","district_code":"120819","name":"BAHALAT BAYU","postal_code":"21153"},{"code":"1208192004","district_code":"120819","name":"MEKAR BAHALAT","postal_code":"21153"},{"code":"1208192005","district_code":"120819","name":"TANJUNG MARAJA","postal_code":"21153"},{"code":"1208192006","district_code":"120819","name":"MARIAH JAMBI","postal_code":"21153"},{"code":"1208192007","district_code":"120819","name":"BAH JOGA","postal_code":"21153"},{"code":"1208192008","district_code":"120819","name":"BAH JAMBI","postal_code":"21153"}]