[{"code":"1213111003","district_code":"121311","name":"HUTA GODANG","postal_code":"22999"},{"code":"1213112001","district_code":"121311","name":"ALAHAN KAE","postal_code":"22999"},{"code":"1213112002","district_code":"121311","name":"HABINCARAN","postal_code":"22999"},{"code":"1213112004","district_code":"121311","name":"HUTA PADANG UP","postal_code":"22999"},{"code":"1213112005","district_code":"121311","name":"HUTAIMBARU UP","postal_code":"22999"},{"code":"1213112006","district_code":"121311","name":"MUARA SALADI","postal_code":"22994"},{"code":"1213112007","district_code":"121311","name":"PATAHAJANG","postal_code":"22999"},{"code":"1213112008","district_code":"121311","name":"SIMPANG BANYAK JAE","postal_code":"22999"},{"code":"1213112009","district_code":"121311","name":"SIMPANG BANYAK JULU","postal_code":"22999"},{"code":"1213112010","district_code":"121311","name":"SIMPANG DUHU DOLOK","postal_code":"22999"},{"code":"1213112011","district_code":"121311","name":"SIMPANG DUHU LOMBANG","postal_code":"22999"},{"code":"1213112012","district_code":"121311","name":"SIMPANG PINING","postal_code":"22999"},{"code":"1213112013","district_code":"121311","name":"TOLANG","postal_code":"22999"}]