[{"code":"1271201001","district_code":"127120","name":"GANG BUNTU","postal_code":"20231"},{"code":"1271201002","district_code":"127120","name":"SIDODADI","postal_code":"20234"},{"code":"1271201003","district_code":"127120","name":"DURIAN","postal_code":"20235"},{"code":"1271201004","district_code":"127120","name":"GLUGUR DARAT I","postal_code":"20238"},{"code":"1271201005","district_code":"127120","name":"GLUGUR DARAT II","postal_code":"20238"},{"code":"1271201006","district_code":"127120","name":"P BERAYAN DARAT I","postal_code":"20239"},{"code":"1271201007","district_code":"127120","name":"P BERAYAN DARAT II","postal_code":"20239"},{"code":"1271201008","district_code":"127120","name":"P BERAYAN BENGKEL","postal_code":"20239"},{"code":"1271201009","district_code":"127120","name":"PB BENGKEL BARU","postal_code":"20239"},{"code":"1271201010","district_code":"127120","name":"PERINTIS","postal_code":"20231"},{"code":"1271201011","district_code":"127120","name":"GAHARU","postal_code":"20235"}]