[{"code":"1301022001","district_code":"130102","name":"PELANGAI","postal_code":"25666"},{"code":"1301022002","district_code":"130102","name":"SUNGAI TUNU","postal_code":"25666"},{"code":"1301022003","district_code":"130102","name":"SUNGAI TUNU UTARA","postal_code":"25666"},{"code":"1301022004","district_code":"130102","name":"SUNGAI TUNU BARAT","postal_code":"25666"},{"code":"1301022005","district_code":"130102","name":"NYIUR MELAMBAI PELANGAI","postal_code":"25666"},{"code":"1301022006","district_code":"130102","name":"SUNGAI LIKU PELANGAI","postal_code":"25666"},{"code":"1301022007","district_code":"130102","name":"KOTO VIII PELANGAI","postal_code":"25666"},{"code":"1301022008","district_code":"130102","name":"PELANGAI GADANG","postal_code":"25666"},{"code":"1301022009","district_code":"130102","name":"PELANGAI KACIAK","postal_code":"25666"},{"code":"1301022010","district_code":"130102","name":"PASIA PELANGAI","postal_code":"25666"}]