[{"code":"1401142001","district_code":"140114","name":"PULAU PAYUNG","postal_code":"28458"},{"code":"1401142002","district_code":"140114","name":"TERATAK","postal_code":"28458"},{"code":"1401142003","district_code":"140114","name":"ALAM PANJANG","postal_code":"28458"},{"code":"1401142004","district_code":"140114","name":"BUKIT KRATAI"},{"code":"1401142005","district_code":"140114","name":"BATANG BATINDIH","postal_code":"28458"},{"code":"1401142006","district_code":"140114","name":"TAMBUSAI","postal_code":"28458"},{"code":"1401142007","district_code":"140114","name":"SIMPANG PETAI","postal_code":"28458"}]