[{"code":"1401192001","district_code":"140119","name":"SIMALINYANG","postal_code":"28475"},{"code":"1401192002","district_code":"140119","name":"BINA BARU","postal_code":"28475"},{"code":"1401192003","district_code":"140119","name":"HIDUP BARU","postal_code":"28475"},{"code":"1401192004","district_code":"140119","name":"KARYA BAKTI","postal_code":"28475"},{"code":"1401192005","district_code":"140119","name":"LUBUK SAKAI","postal_code":"28475"},{"code":"1401192006","district_code":"140119","name":"PENGHIDUPAN","postal_code":"28475"},{"code":"1401192007","district_code":"140119","name":"MAYANG PONGKAI","postal_code":"28475"},{"code":"1401192008","district_code":"140119","name":"KOTO DAMAI","postal_code":"28475"},{"code":"1401192009","district_code":"140119","name":"UTAMA KARYA","postal_code":"28475"},{"code":"1401192010","district_code":"140119","name":"BUKIT SAKAI","postal_code":"28475"},{"code":"1401192011","district_code":"140119","name":"MEKAR JAYA","postal_code":"28475"}]