[{"code":"1502051002","district_code":"150205","name":"DUSUN BARU","postal_code":"37350"},{"code":"1502051003","district_code":"150205","name":"PASAR RANTAU PANJANG"},{"code":"1502051005","district_code":"150205","name":"KAMPUNG BARUH","postal_code":"37350"},{"code":"1502051020","district_code":"150205","name":"MAMPUN","postal_code":"37350"},{"code":"1502051036","district_code":"150205","name":"PASAR BARU RANTAU"},{"code":"1502052007","district_code":"150205","name":"KANDANG","postal_code":"37350"},{"code":"1502052008","district_code":"150205","name":"KOTO RAYO","postal_code":"37350"},{"code":"1502052011","district_code":"150205","name":"TANJUNG ILIR","postal_code":"37350"},{"code":"1502052014","district_code":"150205","name":"BELURAN PANJANG","postal_code":"37350"},{"code":"1502052015","district_code":"150205","name":"SELING","postal_code":"37350"},{"code":"1502052035","district_code":"150205","name":"LUBUK NAPAL","postal_code":"37350"}]