[{"code":"1503112001","district_code":"150311","name":"GURUH BARU","postal_code":"37492"},{"code":"1503112002","district_code":"150311","name":"PETIDURAN BARU","postal_code":"37492"},{"code":"1503112003","district_code":"150311","name":"SUNGAI BUTANG","postal_code":"37492"},{"code":"1503112004","district_code":"150311","name":"BUTANG BARU","postal_code":"37492"},{"code":"1503112005","district_code":"150311","name":"SUKA MAJU","postal_code":"37492"},{"code":"1503112006","district_code":"150311","name":"JATI BARU","postal_code":"37492"},{"code":"1503112007","district_code":"150311","name":"JATI BARU MUDO","postal_code":"37492"},{"code":"1503112008","district_code":"150311","name":"MERANTI BARU","postal_code":"37492"},{"code":"1503112009","district_code":"150311","name":"MERANTI JAYA","postal_code":"37492"},{"code":"1503112010","district_code":"150311","name":"JERNANG BARU","postal_code":"37492"}]