[{"code":"1507111001","district_code":"150711","name":"SIMPANG","postal_code":"36751"},{"code":"1507112002","district_code":"150711","name":"RANTAU RASAU"},{"code":"1507112003","district_code":"150711","name":"RANTAU MAKMUR","postal_code":"36751"},{"code":"1507112004","district_code":"150711","name":"SUNGAI RAMBUT","postal_code":"36751"},{"code":"1507112005","district_code":"150711","name":"RAWASARI","postal_code":"36751"},{"code":"1507112006","district_code":"150711","name":"TELAGA LIMO","postal_code":"36751"}]