[{"code":"1601302001","district_code":"160130","name":"BATU MARTA I","postal_code":"32152"},{"code":"1601302002","district_code":"160130","name":"BATU MARTA II","postal_code":"32152"},{"code":"1601302003","district_code":"160130","name":"LEKIS REJO","postal_code":"32152"},{"code":"1601302004","district_code":"160130","name":"LUBUK BANJAR","postal_code":"32152"},{"code":"1601302005","district_code":"160130","name":"MARTA JAYA","postal_code":"32152"},{"code":"1601302006","district_code":"160130","name":"BATU RADEN","postal_code":"32152"},{"code":"1601302007","district_code":"160130","name":"BATTU WINANGUN","postal_code":"32152"}]