[{"code":"1604192001","district_code":"160419","name":"SAUNG NAGA","postal_code":"31452"},{"code":"1604192002","district_code":"160419","name":"PENANTIAN","postal_code":"31452"},{"code":"1604192003","district_code":"160419","name":"SUKA MERINDU","postal_code":"31452"},{"code":"1604192004","district_code":"160419","name":"JAJARAN BARU","postal_code":"31452"},{"code":"1604192005","district_code":"160419","name":"WONOREJO","postal_code":"31452"},{"code":"1604192006","district_code":"160419","name":"BABATAN BARU","postal_code":"31452"},{"code":"1604192007","district_code":"160419","name":"JAJARAN LAMA","postal_code":"31452"},{"code":"1604192008","district_code":"160419","name":"LUBUK SEKETI","postal_code":"31452"},{"code":"1604192009","district_code":"160419","name":"SUKARAMI","postal_code":"31452"},{"code":"1604192010","district_code":"160419","name":"SINGAPURA","postal_code":"31452"},{"code":"1604192011","district_code":"160419","name":"ULAK BANDUNG","postal_code":"31452"},{"code":"1604192012","district_code":"160419","name":"BANDAR JAYA","postal_code":"31452"},{"code":"1604192013","district_code":"160419","name":"PURNAMA SARI","postal_code":"31452"},{"code":"1604192014","district_code":"160419","name":"WANARAYA","postal_code":"31452"},{"code":"1604192015","district_code":"160419","name":"PURWOREJO","postal_code":"31452"},{"code":"1604192016","district_code":"160419","name":"SUKA BAKTI","postal_code":"31452"},{"code":"1604192017","district_code":"160419","name":"MEKAR JAYA","postal_code":"31452"},{"code":"1604192018","district_code":"160419","name":"DARMA RAHARJA","postal_code":"31452"},{"code":"1604192019","district_code":"160419","name":"SIDO MAKMUR","postal_code":"31452"}]