[{"code":"1605021019","district_code":"160502","name":"MUARA LAKITAN","postal_code":"31666"},{"code":"1605022001","district_code":"160502","name":"TRI ANGGUN JAYA","postal_code":"31666"},{"code":"1605022002","district_code":"160502","name":"SEMANGUS","postal_code":"31666"},{"code":"1605022003","district_code":"160502","name":"ANYAR","postal_code":"31666"},{"code":"1605022004","district_code":"160502","name":"MUARA RENGAS","postal_code":"31666"},{"code":"1605022005","district_code":"160502","name":"SUNGAI PINANG","postal_code":"31666"},{"code":"1605022006","district_code":"160502","name":"SEMETEH","postal_code":"31666"},{"code":"1605022007","district_code":"160502","name":"PRABUMULIH II","postal_code":"31666"},{"code":"1605022008","district_code":"160502","name":"PRABUMULIH I","postal_code":"31666"},{"code":"1605022009","district_code":"160502","name":"LUBUK PANDAN","postal_code":"31666"},{"code":"1605022010","district_code":"160502","name":"PELITA JAYA","postal_code":"31666"},{"code":"1605022011","district_code":"160502","name":"SIDOMULYO","postal_code":"31666"},{"code":"1605022012","district_code":"160502","name":"MARGA BARU","postal_code":"31666"},{"code":"1605022013","district_code":"160502","name":"PENDINGAN","postal_code":"31666"},{"code":"1605022014","district_code":"160502","name":"BUMI MAKMUR","postal_code":"31666"},{"code":"1605022015","district_code":"160502","name":"MUKTI KARYA","postal_code":"31666"},{"code":"1605022016","district_code":"160502","name":"HARAPAN MAKMUR","postal_code":"31666"},{"code":"1605022017","district_code":"160502","name":"PIAN RAYA","postal_code":"31666"},{"code":"1605022018","district_code":"160502","name":"SINDANG LAYA","postal_code":"31666"},{"code":"1605022020","district_code":"160502","name":"SEMANGGUS BARU","postal_code":"31666"}]