[{"code":"1607142001","district_code":"160714","name":"AIR SOLOK BATU","postal_code":"30973"},{"code":"1607142002","district_code":"160714","name":"SRI MULYO","postal_code":"30973"},{"code":"1607142003","district_code":"160714","name":"SRIKATON","postal_code":"32360"},{"code":"1607142004","district_code":"160714","name":"SIDOHARJO","postal_code":"31662"},{"code":"1607142005","district_code":"160714","name":"BINTARAN","postal_code":"30973"},{"code":"1607142006","district_code":"160714","name":"DAMAR WULAN","postal_code":"30973"},{"code":"1607142007","district_code":"160714","name":"ENGGAL REJO","postal_code":"30973"},{"code":"1607142008","district_code":"160714","name":"SALEH JAYA","postal_code":"30973"},{"code":"1607142009","district_code":"160714","name":"SALEH AGUNG","postal_code":"30973"},{"code":"1607142010","district_code":"160714","name":"SALEH MULYA","postal_code":"30973"},{"code":"1607142011","district_code":"160714","name":"SALEH MUKTI","postal_code":"30973"},{"code":"1607142012","district_code":"160714","name":"SALEH MAKMUR","postal_code":"30973"},{"code":"1607142013","district_code":"160714","name":"UPANG","postal_code":"30973"},{"code":"1607142014","district_code":"160714","name":"UPANG MARGA","postal_code":"30973"}]