[{"code":"1703232001","district_code":"170323","name":"AIR LELANGI","postal_code":"38364"},{"code":"1703232002","district_code":"170323","name":"BUKIT BERLIAN","postal_code":"38364"},{"code":"1703232003","district_code":"170323","name":"TANJUNG DALAM","postal_code":"38364"},{"code":"1703232004","district_code":"170323","name":"BUKIT SARI","postal_code":"38364"},{"code":"1703232005","district_code":"170323","name":"PAGARDIN","postal_code":"38364"},{"code":"1703232006","district_code":"170323","name":"TANJUNG HARAPAN","postal_code":"38364"},{"code":"1703232007","district_code":"170323","name":"TANJUNG SARI","postal_code":"38364"},{"code":"1703232008","district_code":"170323","name":"BANGUN KARYA","postal_code":"38364"},{"code":"1703232009","district_code":"170323","name":"PONDOK BAKIL","postal_code":"38364"},{"code":"1703232010","district_code":"170323","name":"TALANG BERANTAI","postal_code":"38364"}]