[{"code":"1703132003","district_code":"170313","name":"TANJUNG ALAI","postal_code":"22998"},{"code":"1703132004","district_code":"170313","name":"JABI","postal_code":"38363"},{"code":"1703132005","district_code":"170313","name":"NAPAL PUTIH","postal_code":"38363"},{"code":"1703132006","district_code":"170313","name":"AIR TENANG","postal_code":"38363"},{"code":"1703132007","district_code":"170313","name":"TELUK ANGGUNG","postal_code":"38363"},{"code":"1703132008","district_code":"170313","name":"TANJUNG KEMAYAN"},{"code":"1703132009","district_code":"170313","name":"MUARA SANTAN","postal_code":"38363"},{"code":"1703132016","district_code":"170313","name":"LEBONG TANDAI","postal_code":"38363"},{"code":"1703132019","district_code":"170313","name":"GEMBUNG RAYA","postal_code":"38363"},{"code":"1703132020","district_code":"170313","name":"KINAL JAYA","postal_code":"38363"}]