[{"code":"1802272001","district_code":"180227","name":"GEDUNG SARI","postal_code":"35513"},{"code":"1802272002","district_code":"180227","name":"SRIMULYO","postal_code":"35513"},{"code":"1802272003","district_code":"180227","name":"GEDUNG RATU","postal_code":"35513"},{"code":"1802272004","district_code":"180227","name":"BANDAR PUTIH TUA","postal_code":"35513"},{"code":"1802272005","district_code":"180227","name":"KARANG JAWA","postal_code":"35513"},{"code":"1802272006","district_code":"180227","name":"SUKAJAYA","postal_code":"35513"}]