[{"code":"1806272001","district_code":"180627","name":"SUKAMARA","postal_code":"35682"},{"code":"1806272002","district_code":"180627","name":"SUKANEGARA","postal_code":"35682"},{"code":"1806272003","district_code":"180627","name":"BANJARMASIN","postal_code":"42264"},{"code":"1806272004","district_code":"180627","name":"SUKA AGUNG BARAT","postal_code":"35682"},{"code":"1806272005","district_code":"180627","name":"SUKA AGUNG","postal_code":"35682"},{"code":"1806272006","district_code":"180627","name":"GUNUNG TERANG","postal_code":"35682"},{"code":"1806272007","district_code":"180627","name":"NAPAL","postal_code":"35682"},{"code":"1806272008","district_code":"180627","name":"SINAR PETIR","postal_code":"35682"},{"code":"1806272009","district_code":"180627","name":"PEMATANG NEBAK","postal_code":"35682"},{"code":"1806272010","district_code":"180627","name":"TANJUNG SARI","postal_code":"35682"}]