[{"code":"3202172001","district_code":"320217","name":"PONDOKKASO TONGGOH"},{"code":"3202172002","district_code":"320217","name":"BABAKANPARI","postal_code":"43358"},{"code":"3202172003","district_code":"320217","name":"PONDOKKASO TENGAH"},{"code":"3202172004","district_code":"320217","name":"CIDAHU","postal_code":"43358"},{"code":"3202172005","district_code":"320217","name":"TANGKIL","postal_code":"43358"},{"code":"3202172006","district_code":"320217","name":"JAYABAKTI","postal_code":"43358"},{"code":"3202172007","district_code":"320217","name":"GIRIJAYA","postal_code":"43358"},{"code":"3202172008","district_code":"320217","name":"PASIRDOTON","postal_code":"43358"}]