[{"code":"3205212001","district_code":"320521","name":"SUKARESMI","postal_code":"44154"},{"code":"3205212002","district_code":"320521","name":"CINTADAMAI","postal_code":"44154"},{"code":"3205212003","district_code":"320521","name":"MEKARJAYA","postal_code":"44154"},{"code":"3205212004","district_code":"320521","name":"SUKAJAYA","postal_code":"44154"},{"code":"3205212005","district_code":"320521","name":"SUKAMULYA","postal_code":"44154"},{"code":"3205212006","district_code":"320521","name":"PADAMUKTI","postal_code":"44154"},{"code":"3205212007","district_code":"320521","name":"SUKALILAH","postal_code":"44154"}]