[{"code":"3273161001","district_code":"327316","name":"SUKAPURA","postal_code":"40285"},{"code":"3273161002","district_code":"327316","name":"KEBON JAYANTI"},{"code":"3273161003","district_code":"327316","name":"BABAKAN SURABAYA","postal_code":"40281"},{"code":"3273161004","district_code":"327316","name":"CICAHEUM","postal_code":"40282"},{"code":"3273161005","district_code":"327316","name":"BABAKAN SARI"},{"code":"3273161006","district_code":"327316","name":"KEBON KANGKUNG","postal_code":"40284"}]