[{"code":"3301192001","district_code":"330119","name":"PATIMUAN","postal_code":"53264"},{"code":"3301192002","district_code":"330119","name":"RAWAAPU","postal_code":"53264"},{"code":"3301192003","district_code":"330119","name":"SIDAMUKTI","postal_code":"53264"},{"code":"3301192004","district_code":"330119","name":"PURWADADI","postal_code":"53264"},{"code":"3301192005","district_code":"330119","name":"CINYAWANG","postal_code":"53264"},{"code":"3301192006","district_code":"330119","name":"BULUPAYUNG","postal_code":"53264"},{"code":"3301192007","district_code":"330119","name":"CIMRUTU","postal_code":"53264"}]