[{"code":"3329132001","district_code":"332913","name":"KARANGREJA","postal_code":"52254"},{"code":"3329132002","district_code":"332913","name":"KEDAWUNG","postal_code":"52254"},{"code":"3329132003","district_code":"332913","name":"KEMURANG KULON","postal_code":"52254"},{"code":"3329132004","district_code":"332913","name":"KEMURANG WETAN","postal_code":"52254"},{"code":"3329132005","district_code":"332913","name":"KRAKAHAN","postal_code":"52254"},{"code":"3329132006","district_code":"332913","name":"KUBANGPUTAT"},{"code":"3329132007","district_code":"332913","name":"LUWUNGGEDE","postal_code":"52254"},{"code":"3329132008","district_code":"332913","name":"LEMAHABANG","postal_code":"52254"},{"code":"3329132009","district_code":"332913","name":"LUWUNGBATA","postal_code":"52254"},{"code":"3329132010","district_code":"332913","name":"MUNDU","postal_code":"52254"},{"code":"3329132011","district_code":"332913","name":"PEJAGAN","postal_code":"52254"},{"code":"3329132012","district_code":"332913","name":"PENGARADAN","postal_code":"52254"},{"code":"3329132013","district_code":"332913","name":"SARIREJA","postal_code":"52254"},{"code":"3329132014","district_code":"332913","name":"SENGON","postal_code":"52254"},{"code":"3329132015","district_code":"332913","name":"SIDAKATON","postal_code":"52254"},{"code":"3329132016","district_code":"332913","name":"TANJUNG","postal_code":"52254"},{"code":"3329132017","district_code":"332913","name":"TEGONGAN","postal_code":"52254"},{"code":"3329132018","district_code":"332913","name":"TENGGULI","postal_code":"52254"}]