[{"code":"3504082001","district_code":"350408","name":"BUNGUR","postal_code":"66253"},{"code":"3504082002","district_code":"350408","name":"BABADAN","postal_code":"66253"},{"code":"3504082003","district_code":"350408","name":"SUKOWIYONO","postal_code":"66253"},{"code":"3504082004","district_code":"350408","name":"SEMBON","postal_code":"66253"},{"code":"3504082005","district_code":"350408","name":"SUKOWIDODO","postal_code":"66253"},{"code":"3504082006","district_code":"350408","name":"TANJUNGSARI","postal_code":"66253"},{"code":"3504082007","district_code":"350408","name":"GEDANGAN","postal_code":"66253"},{"code":"3504082008","district_code":"350408","name":"SUKODONO","postal_code":"66253"},{"code":"3504082009","district_code":"350408","name":"KARANGREJO","postal_code":"66253"},{"code":"3504082010","district_code":"350408","name":"SUKOREJO","postal_code":"66253"},{"code":"3504082011","district_code":"350408","name":"PUNJUL","postal_code":"66253"},{"code":"3504082012","district_code":"350408","name":"JELI","postal_code":"66253"},{"code":"3504082013","district_code":"350408","name":"TULUNGREJO","postal_code":"66253"}]