[{"code":"3522282001","district_code":"352228","name":"GAYAM","postal_code":"62154"},{"code":"3522282002","district_code":"352228","name":"BEGADON","postal_code":"62154"},{"code":"3522282003","district_code":"352228","name":"RINGINTUNGGAL","postal_code":"62154"},{"code":"3522282004","district_code":"352228","name":"MOJODELIK","postal_code":"62154"},{"code":"3522282005","district_code":"352228","name":"BRABOWAN","postal_code":"62154"},{"code":"3522282006","district_code":"352228","name":"BONOREJO","postal_code":"62154"},{"code":"3522282007","district_code":"352228","name":"BEGED","postal_code":"62152"},{"code":"3522282008","district_code":"352228","name":"KATUR","postal_code":"62152"},{"code":"3522282009","district_code":"352228","name":"NGRAHO","postal_code":"62152"},{"code":"3522282010","district_code":"352228","name":"SUDU","postal_code":"62152"},{"code":"3522282011","district_code":"352228","name":"CENGUNGKLUNG","postal_code":"62152"},{"code":"3522282012","district_code":"352228","name":"MANUKAN","postal_code":"62152"}]