[{"code":"3525012001","district_code":"352501","name":"SAWO","postal_code":"61155"},{"code":"3525012002","district_code":"352501","name":"KARANGCANGKRING","postal_code":"61155"},{"code":"3525012003","district_code":"352501","name":"GEDONGKEDO'AN","postal_code":"61155"},{"code":"3525012004","district_code":"352501","name":"BULANGAN","postal_code":"61155"},{"code":"3525012005","district_code":"352501","name":"WONOKERTO","postal_code":"61155"},{"code":"3525012006","district_code":"352501","name":"BANGERAN","postal_code":"61155"},{"code":"3525012007","district_code":"352501","name":"LOWAYU","postal_code":"61155"},{"code":"3525012008","district_code":"352501","name":"PETIYIN TUNGGAL","postal_code":"61155"},{"code":"3525012009","district_code":"352501","name":"TIREM ENGGAL","postal_code":"61155"},{"code":"3525012010","district_code":"352501","name":"TEBUWUNG","postal_code":"61155"},{"code":"3525012011","district_code":"352501","name":"DUKUH KEMBAR","postal_code":"61155"},{"code":"3525012012","district_code":"352501","name":"MADUMULYOREJO","postal_code":"61155"},{"code":"3525012013","district_code":"352501","name":"MENTARAS","postal_code":"61155"},{"code":"3525012014","district_code":"352501","name":"BARON","postal_code":"61155"},{"code":"3525012015","district_code":"352501","name":"JREBENG","postal_code":"61155"},{"code":"3525012016","district_code":"352501","name":"MOJOPETUNG","postal_code":"61155"},{"code":"3525012017","district_code":"352501","name":"SEKARGADUNG","postal_code":"61155"},{"code":"3525012018","district_code":"352501","name":"IMA'AN"},{"code":"3525012019","district_code":"352501","name":"BABAKBAWO","postal_code":"61155"},{"code":"3525012020","district_code":"352501","name":"BABAKSARI","postal_code":"61155"},{"code":"3525012021","district_code":"352501","name":"SAMBOGUNUNG","postal_code":"61155"},{"code":"3525012022","district_code":"352501","name":"SEMBUNGAN KIDUL","postal_code":"61155"},{"code":"3525012023","district_code":"352501","name":"SEMBUNGANYAR","postal_code":"61155"},{"code":"3525012024","district_code":"352501","name":"KALIREJO","postal_code":"61155"},{"code":"3525012025","district_code":"352501","name":"PADANG BANDUNG","postal_code":"61155"},{"code":"3525012026","district_code":"352501","name":"DUKUNANYAR","postal_code":"61155"}]