[{"code":"3528132001","district_code":"352813","name":"SANA TENGAH","postal_code":"69356"},{"code":"3528132002","district_code":"352813","name":"SANA DAJA"},{"code":"3528132003","district_code":"352813","name":"TAGANGSER DAJA"},{"code":"3528132004","district_code":"352813","name":"SOTABAR","postal_code":"69356"},{"code":"3528132005","district_code":"352813","name":"TLONTO RAJA","postal_code":"69356"},{"code":"3528132006","district_code":"352813","name":"DEMPO BARAT","postal_code":"69356"},{"code":"3528132007","district_code":"352813","name":"DEMPO TIMUR","postal_code":"69356"},{"code":"3528132008","district_code":"352813","name":"BINDANG","postal_code":"69356"},{"code":"3528132009","district_code":"352813","name":"BATOKERBUY"}]