[{"code":"5371051001","district_code":"537105","name":"BAKUNASE","postal_code":"85116"},{"code":"5371051002","district_code":"537105","name":"BAKUNASE DUA","postal_code":"85116"},{"code":"5371051003","district_code":"537105","name":"AIRNONA","postal_code":"85119"},{"code":"5371051004","district_code":"537105","name":"NAIKOTEN SATU","postal_code":"85118"},{"code":"5371051005","district_code":"537105","name":"NAIKOTEN DUA","postal_code":"85118"},{"code":"5371051006","district_code":"537105","name":"KUANINO","postal_code":"85119"},{"code":"5371051007","district_code":"537105","name":"NUNLEU","postal_code":"85119"},{"code":"5371051008","district_code":"537105","name":"FONTEIN","postal_code":"85112"}]