[{"code":"6101032001","district_code":"610103","name":"SARANG BURUNG DANAU","postal_code":"79454"},{"code":"6101032002","district_code":"610103","name":"SUNGAI NILAM","postal_code":"79454"},{"code":"6101032003","district_code":"610103","name":"SARANG BURUNG KOLAM","postal_code":"79454"},{"code":"6101032004","district_code":"610103","name":"SARANG BURUNG USRAT","postal_code":"79454"},{"code":"6101032005","district_code":"610103","name":"SARANG BURUNG KUALA","postal_code":"79454"},{"code":"6101032006","district_code":"610103","name":"PELIMPAAN","postal_code":"79454"},{"code":"6101032007","district_code":"610103","name":"PARIT SETIA","postal_code":"79454"},{"code":"6101032008","district_code":"610103","name":"BAKAU","postal_code":"79454"},{"code":"6101032009","district_code":"610103","name":"SUNGAI NYIRIH","postal_code":"79454"},{"code":"6101032010","district_code":"610103","name":"SENTEBANG","postal_code":"79454"},{"code":"6101032011","district_code":"610103","name":"DUNGUN LAUT","postal_code":"79454"},{"code":"6101032021","district_code":"610103","name":"LAMBAU","postal_code":"79454"},{"code":"6101032022","district_code":"610103","name":"MUTUS DARUSSALAM","postal_code":"79454"}]