[{"code":"6310042003","district_code":"631004","name":"SETARAP","postal_code":"72276"},{"code":"6310042004","district_code":"631004","name":"SATUI TIMUR","postal_code":"72276"},{"code":"6310042005","district_code":"631004","name":"SUNGAICUKA","postal_code":"72276"},{"code":"6310042006","district_code":"631004","name":"JOMBANG","postal_code":"72276"},{"code":"6310042008","district_code":"631004","name":"SATUI BARAT","postal_code":"72276"},{"code":"6310042009","district_code":"631004","name":"SEKAPUK","postal_code":"72276"},{"code":"6310042010","district_code":"631004","name":"SUNGAIDANAU","postal_code":"72276"},{"code":"6310042011","district_code":"631004","name":"WONOREJO","postal_code":"72276"},{"code":"6310042012","district_code":"631004","name":"SUMBER MAKMUR","postal_code":"72276"},{"code":"6310042013","district_code":"631004","name":"TEGAL SARI","postal_code":"72276"},{"code":"6310042019","district_code":"631004","name":"SUMBER ARUM","postal_code":"72276"},{"code":"6310042022","district_code":"631004","name":"SEJAHTERA MULIA","postal_code":"72276"},{"code":"6310042023","district_code":"631004","name":"AL KAUTSAR","postal_code":"72276"},{"code":"6310042024","district_code":"631004","name":"MAKMUR MULIA","postal_code":"72276"},{"code":"6310042025","district_code":"631004","name":"SINAR BULAN","postal_code":"72276"},{"code":"6310042026","district_code":"631004","name":"PANDAMARAN JAYA","postal_code":"72276"},{"code":"6310042027","district_code":"631004","name":"SIDO REJO","postal_code":"72276"},{"code":"6310042028","district_code":"631004","name":"BERUNTUNG RAYA","postal_code":"72276"},{"code":"6310042029","district_code":"631004","name":"BARAKAT MUFAKAT"},{"code":"6310042030","district_code":"631004","name":"MAKMUR JAYA","postal_code":"72276"}]