[{"code":"7316021001","district_code":"731602","name":"GALONTA","postal_code":"91712"},{"code":"7316021002","district_code":"731602","name":"JUPPANDANG","postal_code":"91711"},{"code":"7316021003","district_code":"731602","name":"PUSERREN","postal_code":"91711"},{"code":"7316021004","district_code":"731602","name":"LEWAJA","postal_code":"91711"},{"code":"7316021010","district_code":"731602","name":"LEORAN","postal_code":"91711"},{"code":"7316021016","district_code":"731602","name":"TUARA","postal_code":"91711"},{"code":"7316022005","district_code":"731602","name":"RANGA","postal_code":"91711"},{"code":"7316022006","district_code":"731602","name":"BUTTU BATU","postal_code":"91711"},{"code":"7316022007","district_code":"731602","name":"TOKKONAN","postal_code":"91711"},{"code":"7316022008","district_code":"731602","name":"KARUENG","postal_code":"91711"},{"code":"7316022011","district_code":"731602","name":"TALLU BAMBA","postal_code":"91711"},{"code":"7316022012","district_code":"731602","name":"TUNGKA","postal_code":"91711"},{"code":"7316022013","district_code":"731602","name":"KALUPPINI","postal_code":"91711"},{"code":"7316022014","district_code":"731602","name":"TOBALU","postal_code":"91711"},{"code":"7316022015","district_code":"731602","name":"CEMBA","postal_code":"91711"},{"code":"7316022017","district_code":"731602","name":"TEMBAN","postal_code":"91711"},{"code":"7316022018","district_code":"731602","name":"ROSOAN","postal_code":"91711"},{"code":"7316022019","district_code":"731602","name":"LEMBANG","postal_code":"91711"}]