[{"code":"7326101002","district_code":"732610","name":"TAGARI","postal_code":"91855"},{"code":"7326101005","district_code":"732610","name":"BALUSU","postal_code":"91855"},{"code":"7326102001","district_code":"732610","name":"PALANGI'","postal_code":"91855"},{"code":"7326102003","district_code":"732610","name":"LILIKIRA AO'GADING"},{"code":"7326102004","district_code":"732610","name":"KARUA","postal_code":"91855"},{"code":"7326102006","district_code":"732610","name":"AWA' KAWASIK","postal_code":"91855"},{"code":"7326102007","district_code":"732610","name":"BALUSU BANGUNLIPU","postal_code":"91855"}]