[{"code":"7410011008","district_code":"741001","name":"BANGKUDU","postal_code":"93672"},{"code":"7410011009","district_code":"741001","name":"LIPU","postal_code":"93672"},{"code":"7410011010","district_code":"741001","name":"LAKONEA","postal_code":"93672"},{"code":"7410011012","district_code":"741001","name":"LEMO","postal_code":"93672"},{"code":"7410011014","district_code":"741001","name":"BONELIPU","postal_code":"93672"},{"code":"7410011016","district_code":"741001","name":"SARA'EA","postal_code":"93672"},{"code":"7410011017","district_code":"741001","name":"WANDAKA","postal_code":"93672"},{"code":"7410012001","district_code":"741001","name":"TRI WACU-WACU","postal_code":"93672"},{"code":"7410012002","district_code":"741001","name":"WACULAEA","postal_code":"93672"},{"code":"7410012003","district_code":"741001","name":"EELAHAJI","postal_code":"93672"},{"code":"7410012004","district_code":"741001","name":"TOMOAHI","postal_code":"93672"},{"code":"7410012005","district_code":"741001","name":"KALIBU","postal_code":"93672"},{"code":"7410012006","district_code":"741001","name":"JAMPAKA","postal_code":"93672"},{"code":"7410012007","district_code":"741001","name":"LOJI","postal_code":"93672"},{"code":"7410012011","district_code":"741001","name":"LINSOWU","postal_code":"93672"},{"code":"7410012013","district_code":"741001","name":"ROMBO","postal_code":"93672"},{"code":"7410012018","district_code":"741001","name":"WASALABOSE","postal_code":"93672"},{"code":"7410012019","district_code":"741001","name":"MALALANDA","postal_code":"93672"},{"code":"7410012020","district_code":"741001","name":"LEMO EA","postal_code":"93672"},{"code":"7410012021","district_code":"741001","name":"LANTAGI","postal_code":"93672"},{"code":"7410012022","district_code":"741001","name":"LAANGKE","postal_code":"93672"},{"code":"7410012023","district_code":"741001","name":"KADACUA","postal_code":"93672"},{"code":"7410012024","district_code":"741001","name":"BANU-BANUA JAYA","postal_code":"93672"}]