[{"code":"8104032001","district_code":"810403","name":"SAVANA JAYA","postal_code":"97578"},{"code":"8104032002","district_code":"810403","name":"WAETELE","postal_code":"97578"},{"code":"8104032003","district_code":"810403","name":"WAEKASAR","postal_code":"97578"},{"code":"8104032004","district_code":"810403","name":"WAENETAT","postal_code":"97578"},{"code":"8104032016","district_code":"810403","name":"WAEKERTA","postal_code":"97578"},{"code":"8104032019","district_code":"810403","name":"WANAREJA","postal_code":"97578"},{"code":"8104032027","district_code":"810403","name":"GOGOREA","postal_code":"97578"}]