[{"code":"9119042001","district_code":"911904","name":"RAYORI","postal_code":"98571"},{"code":"9119042002","district_code":"911904","name":"MBRURWANDI","postal_code":"98571"},{"code":"9119042003","district_code":"911904","name":"MANGGONSWAN","postal_code":"98571"},{"code":"9119042004","district_code":"911904","name":"WONGKEINA","postal_code":"98571"},{"code":"9119042005","district_code":"911904","name":"YAMNAISU","postal_code":"98571"},{"code":"9119042006","district_code":"911904","name":"ARURI","postal_code":"98571"},{"code":"9119042007","district_code":"911904","name":"IMBIRSBARI","postal_code":"98571"},{"code":"9119042008","district_code":"911904","name":"INEKI","postal_code":"98571"},{"code":"9119042009","district_code":"911904","name":"INSUMBREI","postal_code":"98571"}]