[{"code":"9302022001","district_code":"930202","name":"MINDIPTANA","postal_code":"99663"},{"code":"9302022002","district_code":"930202","name":"UMAP","postal_code":"99663"},{"code":"9302022003","district_code":"930202","name":"AWAYANKA","postal_code":"99663"},{"code":"9302022004","district_code":"930202","name":"WANGGATKIBI","postal_code":"99663"},{"code":"9302022005","district_code":"930202","name":"EPSEMBIT","postal_code":"99663"},{"code":"9302022006","district_code":"930202","name":"ANDOBIT","postal_code":"99663"},{"code":"9302022007","district_code":"930202","name":"NIYIMBANG","postal_code":"99663"},{"code":"9302022008","district_code":"930202","name":"ANGGUMBIT","postal_code":"99663"},{"code":"9302022009","district_code":"930202","name":"IMKO","postal_code":"99663"},{"code":"9302022010","district_code":"930202","name":"KAMKA","postal_code":"99663"},{"code":"9302022011","district_code":"930202","name":"OSSO","postal_code":"99663"},{"code":"9302022012","district_code":"930202","name":"TINGGAM","postal_code":"99663"},{"code":"9302022013","district_code":"930202","name":"KAKUNA","postal_code":"99663"}]