[{"code":"9402032001","district_code":"940203","name":"FAWI","postal_code":"98942"},{"code":"9402032002","district_code":"940203","name":"BAKUSI","postal_code":"98942"},{"code":"9402032003","district_code":"940203","name":"TURUMO","postal_code":"98942"},{"code":"9402032004","district_code":"940203","name":"KAHO","postal_code":"98942"},{"code":"9402032005","district_code":"940203","name":"BIRICARE","postal_code":"98942"},{"code":"9402032006","district_code":"940203","name":"DOREY","postal_code":"98942"},{"code":"9402032007","district_code":"940203","name":"FII","postal_code":"98942"},{"code":"9402032008","district_code":"940203","name":"EVO","postal_code":"98942"},{"code":"9402032009","district_code":"940203","name":"YEREI","postal_code":"98942"}]