[{"code":"9505012001","district_code":"950501","name":"KOBAKMA","postal_code":"99074"},{"code":"9505012002","district_code":"950501","name":"NINUGAGAS","postal_code":"99074"},{"code":"9505012003","district_code":"950501","name":"SERALEMA","postal_code":"99074"},{"code":"9505012004","district_code":"950501","name":"GIMBIS","postal_code":"99074"},{"code":"9505012005","district_code":"950501","name":"BOROGES","postal_code":"99074"},{"code":"9505012006","district_code":"950501","name":"AUNDUANG","postal_code":"99074"},{"code":"9505012007","district_code":"950501","name":"LUARIMA","postal_code":"99074"},{"code":"9505012008","district_code":"950501","name":"GUAWAGE","postal_code":"99074"},{"code":"9505012009","district_code":"950501","name":"MOGA","postal_code":"99074"},{"code":"9505012010","district_code":"950501","name":"KENIWA","postal_code":"99074"},{"code":"9505012011","district_code":"950501","name":"SEMBEGULIK","postal_code":"99074"},{"code":"9505012012","district_code":"950501","name":"DOGLE","postal_code":"99074"},{"code":"9505012013","district_code":"950501","name":"WIYUGOBAK","postal_code":"99074"},{"code":"9505012014","district_code":"950501","name":"BALIKLABUK","postal_code":"99074"},{"code":"9505012015","district_code":"950501","name":"YAGALIM","postal_code":"99074"}]