[{"code":"9605032001","district_code":"960503","name":"AISA","postal_code":"98273"},{"code":"9605032002","district_code":"960503","name":"AIKRER","postal_code":"98273"},{"code":"9605032003","district_code":"960503","name":"AITREM","postal_code":"98273"},{"code":"9605032004","district_code":"960503","name":"SAWIN","postal_code":"98273"},{"code":"9605032005","district_code":"960503","name":"SAHBUKU","postal_code":"98273"},{"code":"9605032006","district_code":"960503","name":"SASIOR FRABUKU","postal_code":"98273"},{"code":"9605032007","district_code":"960503","name":"WAKOM","postal_code":"98273"},{"code":"9605032008","district_code":"960503","name":"SANEM","postal_code":"98273"},{"code":"9605032009","district_code":"960503","name":"BUOH SA","postal_code":"98273"}]