[{"code":"130804","regency_code":"1308","name":"BONJOL"},{"code":"130805","regency_code":"1308","name":"LUBUK SIKAPING"},{"code":"130807","regency_code":"1308","name":"PANTI"},{"code":"130808","regency_code":"1308","name":"MAPAT TUNGGUL"},{"code":"130812","regency_code":"1308","name":"DUO KOTO"},{"code":"130813","regency_code":"1308","name":"TIGO NAGARI"},{"code":"130814","regency_code":"1308","name":"RAO"},{"code":"130815","regency_code":"1308","name":"MAPAT TUNGGUL SELATAN"},{"code":"130816","regency_code":"1308","name":"SIMPANG ALAHAN MATI"},{"code":"130817","regency_code":"1308","name":"PADANG GELUGUR"},{"code":"130818","regency_code":"1308","name":"RAO UTARA"},{"code":"130819","regency_code":"1308","name":"RAO SELATAN"}]