[{"code":"150201","regency_code":"1502","name":"JANGKAT"},{"code":"150202","regency_code":"1502","name":"BANGKO"},{"code":"150203","regency_code":"1502","name":"MUARA SIAU"},{"code":"150204","regency_code":"1502","name":"SUNGAI MANAU"},{"code":"150205","regency_code":"1502","name":"TABIR"},{"code":"150206","regency_code":"1502","name":"PAMENANG"},{"code":"150207","regency_code":"1502","name":"TABIR ULU"},{"code":"150208","regency_code":"1502","name":"TABIR SELATAN"},{"code":"150209","regency_code":"1502","name":"LEMBAH MASURAI"},{"code":"150210","regency_code":"1502","name":"BANGKO BARAT"},{"code":"150211","regency_code":"1502","name":"NALO TANTAN"},{"code":"150212","regency_code":"1502","name":"BATANG MASUMAI"},{"code":"150213","regency_code":"1502","name":"PAMENANG BARAT"},{"code":"150214","regency_code":"1502","name":"TABIR ILIR"},{"code":"150215","regency_code":"1502","name":"TABIR TIMUR"},{"code":"150216","regency_code":"1502","name":"RENAH PEMBARAP"},{"code":"150217","regency_code":"1502","name":"PANGKALAN JAMBU"},{"code":"150218","regency_code":"1502","name":"JANGKAT TIMUR"},{"code":"150219","regency_code":"1502","name":"RENAH PAMENANG"},{"code":"150220","regency_code":"1502","name":"PAMENANG SELATAN"},{"code":"150221","regency_code":"1502","name":"MARGO TABIR"},{"code":"150222","regency_code":"1502","name":"TABIR LINTAS"},{"code":"150223","regency_code":"1502","name":"TABIR BARAT"},{"code":"150224","regency_code":"1502","name":"TIANG PUMPUNG"}]